omnikinverter/__init__.py
omnikinverter/const.py
omnikinverter/exceptions.py
omnikinverter/models.py
omnikinverter/omnikinverter.py
omnikinverter/py.typed
omnikinverter/tcp.py
omnikinverter-1.0.0.dist-info/LICENSE
omnikinverter-1.0.0.dist-info/METADATA
omnikinverter-1.0.0.dist-info/WHEEL
omnikinverter-1.0.0.dist-info/RECORD
