Metadata-Version: 2.1
Name: omnikinverter
Version: 1.0.0
Summary: Asynchronous Python client for the Omnik Inverter
Home-page: https://github.com/klaasnicolaas/python-omnikinverter
License: MIT
Keywords: omnik,inverter,power,energy,async,client
Author: Klaas Schoute
Author-email: hello@student-techlife.com
Maintainer: Klaas Schoute
Maintainer-email: hello@student-techlife.com
Requires-Python: >=3.11,<4.0
Classifier: Development Status :: 5 - Production/Stable
Classifier: Framework :: AsyncIO
Classifier: Intended Audience :: Developers
Classifier: License :: OSI Approved :: MIT License
Classifier: Natural Language :: English
Classifier: Programming Language :: Python :: 3
Classifier: Programming Language :: Python :: 3.11
Classifier: Programming Language :: Python :: 3.12
Classifier: Topic :: Software Development :: Libraries :: Python Modules
Requires-Dist: aiohttp (>=3.0.0)
Requires-Dist: yarl (>=1.6.0)
Project-URL: Bug Tracker, https://github.com/klaasnicolaas/python-omnikinverter/issues
Project-URL: Changelog, https://github.com/klaasnicolaas/python-omnikinverter/releases
Project-URL: Documentation, https://github.com/klaasnicolaas/python-omnikinverter
Project-URL: Repository, https://github.com/klaasnicolaas/python-omnikinverter
